dynamicDML/__init__.py
dynamicDML/_base.py
dynamicDML/_example_data.py
dynamicDML/_flaml_estimators.py
dynamicDML/dml2periods.py
dynamicdml-0.2.0.dist-info/licenses/LICENSE.txt
dynamicdml-0.2.0.dist-info/METADATA
dynamicdml-0.2.0.dist-info/WHEEL
dynamicdml-0.2.0.dist-info/top_level.txt
dynamicdml-0.2.0.dist-info/RECORD
