Metadata-Version: 2.4
Name: dynamicDML
Version: 0.2.0
Summary: A Python implementation of dynamic Double Machine Learning (DML).
Home-page: https://fmuny.github.io/dynamicDML/
Download-URL: https://github.com/fmuny/dynamicDML/archive/refs/tags/v0.2.0.tar.gz
Author: Fabian Muny
License: MIT
Keywords: double machine learning,dynamic policy
Classifier: Development Status :: 4 - Beta
Classifier: Intended Audience :: Science/Research
Classifier: Topic :: Software Development :: Build Tools
Classifier: License :: OSI Approved :: MIT License
Classifier: Programming Language :: Python :: 3.12
License-File: LICENSE.txt
Requires-Dist: flaml[automl]>=2.3.3
Requires-Dist: matplotlib>=3.10.0
Requires-Dist: mgzip>=0.2.1
Requires-Dist: numpy>=2.2.3
Requires-Dist: pandas>=2.2.3
Requires-Dist: scikit-learn>=1.6.1
Requires-Dist: scipy>=1.15.2
Requires-Dist: seaborn>=0.13.2
Dynamic: author
Dynamic: classifier
Dynamic: description
Dynamic: description-content-type
Dynamic: download-url
Dynamic: home-page
Dynamic: keywords
Dynamic: license
Dynamic: license-file
Dynamic: requires-dist
Dynamic: summary
